<?xml version="1.0" encoding="utf-8" ?><dwsync><file name="dhtmlxcalendar_classic.css" server="xray.he.net/public_html/telepathyexperiment/" local="3366614876" remote="20546484060" /><file name="dhtmlxcalendar_dhx_skyblue.css" server="xray.he.net/public_html/telepathyexperiment/" local="3366614878" remote="20546484062" /><file name="dhtmlxcalendar_dhx_blue.css" server="xray.he.net/public_html/telepathyexperiment/" local="3366614878" remote="20546484062" /><file name="dhtmlxcalendar_simplecolordark.css" server="xray.he.net/public_html/telepathyexperiment/" local="3366614878" remote="20546484062" /><file name="dhtmlxcalendar_simpleblue.css" server="xray.he.net/public_html/telepathyexperiment/" local="3366614878" remote="20546484062" /><file name="dhtmlxcalendar_yahoolike.css" server="xray.he.net/public_html/telepathyexperiment/" local="3366614880" remote="20546484064" /><file name="dhtmlxcalendar_simplegrey.css" server="xray.he.net/public_html/telepathyexperiment/" local="3366614880" remote="20546484064" /><file name="dhtmlxcalendar_vista.css" server="xray.he.net/public_html/telepathyexperiment/" local="3366614880" remote="20546484064" /><file name="dhtmlxcalendar_simplecolorsand.css" server="xray.he.net/public_html/telepathyexperiment/" local="3366614880" remote="20546484064" /><file name="dhtmlxcalendar_dhx_black.css" server="xray.he.net/public_html/telepathyexperiment/" local="3366614876" remote="20546484060" /></dwsync>